basic_alu.v
module basic_alu (A, B, op, alu_out);
  input [3:0] A, B;               // 4 bits signals
  input [2:0] op;                 // 3 bits signals
  output reg [3:0] alu_out;
  always@(*)                      //behavioural level modeling
  begin
    case(op)                     // Different Operations for different cases 
      3'b000: alu_out = A+B;
      3'b001: alu_out = A-B;
      3'b010: alu_out = A&B;
      3'b011: alu_out = A|B;
      3'b100: alu_out = ~A;
      3'b101: alu_out = ~B;
      3'b110: alu_out = A^B;
      3'b111: alu_out = A~^B;
      default: alu_out = 0;
    endcase
  end
endmodule

basic_alu_tb.v
// Testbench for the ALU Module

`timescale 1ns/1ps
`include "basic_alu.v"

module basic_alu_tb;

reg [3:0] A, B;    // inputs
reg [2:0] op;      // operations 
wire [3:0] alu_out;  //output

//instantiate the AND GATE module
basic_alu dut(.A(A), .B(B), .op(op), .alu_out(alu_out));

//clock generation
reg clk;
always #5 clk = ~ clk;

//testing the input values
initial begin

$dumpfile("basic_alu_tb.vcd"); //create a cvd file
$dumpvars(0, basic_alu_tb);

// sample input
  A = 3'b0100; // binary value for 4
  B = 3'b0011; // binary value for 3

  op = 000;  // Addition
  #10 $display("ADD %b", alu_out);

  op = 001;  // Subtraction
  #10 $display("SUBTRACT %b", alu_out);

  op = 010;  // AND
  #10 $display("AND %b", alu_out);

  op = 011;  // OR
  #10 $display("OR %b", alu_out);

  op = 100;  // NOT A
  #10 $display("~A %b", alu_out);

  op = 101;  // NOT B
  #10 $display("~B %b", alu_out);

  op = 110;  // XOR
  #10 $display("XOR %b", alu_out);

  op = 111;  // XNOR
  #10 $display("XNOR %b", alu_out);

$finish; // end simulation

end

endmodule

basic_alu_tb.vcd
$date
	Sun Nov 16 19:40:29 2025
$end
$version
	Icarus Verilog
$end
$timescale
	1ps
$end
$scope module basic_alu_tb $end
$var wire 4 ! alu_out [3:0] $end
$var reg 4 " A [3:0] $end
$var reg 4 # B [3:0] $end
$var reg 1 $ clk $end
$var reg 3 % op [2:0] $end
$scope module dut $end
$var wire 4 & A [3:0] $end
$var wire 4 ' B [3:0] $end
$var wire 3 ( op [2:0] $end
$var reg 4 ) alu_out [3:0] $end
$upscope $end
$upscope $end
$enddefinitions $end
$comment Show the parameter values. $end
$dumpall
$end
#0
$dumpvars
b111 )
b0 (
b11 '
b100 &
b0 %
x$
b11 #
b100 "
b111 !
$end
#10000
b1 !
b1 )
b1 %
b1 (
#20000
b0 !
b0 )
b10 %
b10 (
#30000
b111 !
b111 )
b11 %
b11 (
#40000
b1011 !
b1011 )
b100 %
b100 (
#50000
b1100 !
b1100 )
b101 %
b101 (
#60000
b111 !
b111 )
b110 %
b110 (
#70000
b1000 !
b1000 )
b111 %
b111 (
